xeno_canto_utils_nbm/__init__.py
xeno_canto_utils_nbm/xeno_canto_utils.py
xeno_canto_utils_nbm-0.0.19.dist-info/METADATA
xeno_canto_utils_nbm-0.0.19.dist-info/WHEEL
xeno_canto_utils_nbm-0.0.19.dist-info/entry_points.txt
xeno_canto_utils_nbm-0.0.19.dist-info/licenses/LICENSE
xeno_canto_utils_nbm-0.0.19.dist-info/RECORD
