Metadata-Version: 2.3
Name: xeno_canto_utils_nbm
Version: 0.0.19
Summary: Utility functions to interact with the Xeno Canto API with python
Project-URL: Homepage, https://github.com/LouisBearing/BirdSoundClassif
Author-email: Louloulou <laerien@gmail.com>
License: GNU General Public License v3.0
Keywords: machine learning for biology
Requires-Python: >=3.5
Requires-Dist: ffmpeg-python
Requires-Dist: numpy
Requires-Dist: pandas
Requires-Dist: requests
Requires-Dist: tqdm
